dde_ivp/__init__.py
dde_ivp/base.py
dde_ivp/bdf.py
dde_ivp/common.py
dde_ivp/dde_ivp.py
dde_ivp/dop853_coefficients.py
dde_ivp/rk.py
dde_ivp-0.1.3.dist-info/METADATA
dde_ivp-0.1.3.dist-info/WHEEL
dde_ivp-0.1.3.dist-info/top_level.txt
dde_ivp-0.1.3.dist-info/RECORD
