Metadata-Version: 2.1
Name: dde_ivp
Version: 0.1.3
Summary: A package for solving delay differential equations
Author: Dhamdhawach  Horsuwan
Author-email: meng.inventor@gmail.com
Classifier: Programming Language :: Python :: 3
Classifier: License :: OSI Approved :: MIT License
Classifier: Operating System :: OS Independent
Requires-Python: >=3.6
Requires-Dist: numpy
Requires-Dist: matplotlib
Requires-Dist: scipy
